MANIFEST.in
README.md
setup.cfg
setup.py
src/i18n_iso_countries/__init__.py
src/i18n_iso_countries.egg-info/PKG-INFO
src/i18n_iso_countries.egg-info/SOURCES.txt
src/i18n_iso_countries.egg-info/dependency_links.txt
src/i18n_iso_countries.egg-info/not-zip-safe
src/i18n_iso_countries.egg-info/top_level.txt
src/i18n_iso_countries/langs/af.json
src/i18n_iso_countries/langs/am.json
src/i18n_iso_countries/langs/ar.json
src/i18n_iso_countries/langs/az.json
src/i18n_iso_countries/langs/be.json
src/i18n_iso_countries/langs/bg.json
src/i18n_iso_countries/langs/bn.json
src/i18n_iso_countries/langs/bs.json
src/i18n_iso_countries/langs/ca.json
src/i18n_iso_countries/langs/cs.json
src/i18n_iso_countries/langs/da.json
src/i18n_iso_countries/langs/de.json
src/i18n_iso_countries/langs/el.json
src/i18n_iso_countries/langs/en.json
src/i18n_iso_countries/langs/es.json
src/i18n_iso_countries/langs/et.json
src/i18n_iso_countries/langs/eu.json
src/i18n_iso_countries/langs/fa.json
src/i18n_iso_countries/langs/fi.json
src/i18n_iso_countries/langs/fr.json
src/i18n_iso_countries/langs/gl.json
src/i18n_iso_countries/langs/ha.json
src/i18n_iso_countries/langs/he.json
src/i18n_iso_countries/langs/hi.json
src/i18n_iso_countries/langs/hr.json
src/i18n_iso_countries/langs/hu.json
src/i18n_iso_countries/langs/hy.json
src/i18n_iso_countries/langs/id.json
src/i18n_iso_countries/langs/is.json
src/i18n_iso_countries/langs/it.json
src/i18n_iso_countries/langs/ja.json
src/i18n_iso_countries/langs/ka.json
src/i18n_iso_countries/langs/kk.json
src/i18n_iso_countries/langs/km.json
src/i18n_iso_countries/langs/ko.json
src/i18n_iso_countries/langs/ku.json
src/i18n_iso_countries/langs/ky.json
src/i18n_iso_countries/langs/lt.json
src/i18n_iso_countries/langs/lv.json
src/i18n_iso_countries/langs/mk.json
src/i18n_iso_countries/langs/ml.json
src/i18n_iso_countries/langs/mn.json
src/i18n_iso_countries/langs/ms.json
src/i18n_iso_countries/langs/nb.json
src/i18n_iso_countries/langs/nl.json
src/i18n_iso_countries/langs/nn.json
src/i18n_iso_countries/langs/no.json
src/i18n_iso_countries/langs/pl.json
src/i18n_iso_countries/langs/ps.json
src/i18n_iso_countries/langs/pt.json
src/i18n_iso_countries/langs/ro.json
src/i18n_iso_countries/langs/ru.json
