Metadata-Version: 2.1
Name: i18n-iso-countries
Version: 1.0.0
Summary: i18n for ISO 3166-1 country codes. We support Alpha-2, Alpha-3 and Numeric codes
Home-page: https://github.com/pleasurelong/i18n-iso-countries
Author: Jaxon
Author-email: jinlong.wang@protonmail.com
License: MIT
Keywords: countries iso 3166-1
Platform: UNKNOWN
Classifier: Development Status :: 2 - Pre-Alpha
Classifier: License :: OSI Approved :: MIT License
Classifier: Intended Audience :: Developers
Classifier: Operating System :: OS Independent
Classifier: Programming Language :: Python
Classifier: Programming Language :: Python :: 3
Requires-Python: >=3.5, <4
